{
    "lists":[
        {
            "pic":"icons/user2.png",
            "date":"周二",
            "user":"客户七",
            "return":"测试一下下拉刷新"
        },
        {
            "pic":"icons/user3.png",
            "date":"周二",
            "user":"客户一",
            "return":"下拉刷新"
        },
        {
            "pic":"icons/user4.png",
            "date":"周二",
            "user":"客户二",
            "return":"下拉刷新6666"
        },
        {
            "pic":"icons/user5.png",
            "date":"周二",
            "user":"杨叶",
            "return":"下拉刷新正常"
        },
        {
            "pic":"icons/user4.png",
            "date":"周二",
            "user":"Chris",
            "return":"下拉刷新正常！"
        },
        {
            "pic":"icons/user5.png",
            "date":"周二",
            "user":"客户五",
            "return":"下拉刷新正常吗"
        },
        {
            "pic":"icons/user6.png",
            "date":"周二",
            "user":"客户六",
            "return":"正常吧"
        },
        {
            "pic":"icons/user7.png",
            "date":"周二",
            "user":"车友加油",
            "return":"不正常"
        },
        {
            "pic":"icons/user8.png",
            "date":"周二",
            "user":"欧",
            "return":"正常"
        },
        {
            "pic":"icons/user1.png",
            "date":"周二",
            "user":"肯德基宅急送",
            "return":"正常，over"
        }
        {
            "pic":"icons/user2.png",
            "date":"周二",
            "user":"客户七",
            "return":"测试一下下拉刷新"
        },
        {
            "pic":"icons/user3.png",
            "date":"周二",
            "user":"客户一",
            "return":"下拉刷新"
        },
        {
            "pic":"icons/user4.png",
            "date":"周二",
            "user":"客户二",
            "return":"下拉刷新6666"
        },
        {
            "pic":"icons/user5.png",
            "date":"周二",
            "user":"杨叶",
            "return":"下拉刷新正常"
        },
        {
            "pic":"icons/user4.png",
            "date":"周二",
            "user":"Chris",
            "return":"下拉刷新正常！"
        },
        {
            "pic":"icons/user5.png",
            "date":"周二",
            "user":"客户五",
            "return":"下拉刷新正常吗"
        },
        {
            "pic":"icons/user6.png",
            "date":"周二",
            "user":"客户六",
            "return":"正常吧"
        },
        {
            "pic":"icons/user7.png",
            "date":"周二",
            "user":"车友加油",
            "return":"不正常"
        },
        {
            "pic":"icons/user8.png",
            "date":"周二",
            "user":"欧",
            "return":"正常"
        },
        {
            "pic":"icons/user1.png",
            "date":"周二",
            "user":"肯德基宅急送",
            "return":"正常，over"
        }
        {
            "pic":"icons/user2.png",
            "date":"周二",
            "user":"客户七",
            "return":"测试一下下拉刷新"
        },
        {
            "pic":"icons/user3.png",
            "date":"周二",
            "user":"客户一",
            "return":"下拉刷新"
        },
        {
            "pic":"icons/user4.png",
            "date":"周二",
            "user":"客户二",
            "return":"下拉刷新6666"
        },
        {
            "pic":"icons/user5.png",
            "date":"周二",
            "user":"杨叶",
            "return":"下拉刷新正常"
        },
        {
            "pic":"icons/user4.png",
            "date":"周二",
            "user":"Chris",
            "return":"下拉刷新正常！"
        },
        {
            "pic":"icons/user5.png",
            "date":"周二",
            "user":"客户五",
            "return":"下拉刷新正常吗"
        },
        {
            "pic":"icons/user6.png",
            "date":"周二",
            "user":"客户六",
            "return":"正常吧"
        },
        {
            "pic":"icons/user7.png",
            "date":"周二",
            "user":"车友加油",
            "return":"不正常"
        },
        {
            "pic":"icons/user8.png",
            "date":"周二",
            "user":"欧",
            "return":"正常"
        },
        {
            "pic":"icons/user1.png",
            "date":"周二",
            "user":"肯德基宅急送",
            "return":"正常，over"
        }
    ]
}